d3m_automl_rpc/__init__.py
d3m_automl_rpc/core_pb2.py
d3m_automl_rpc/core_pb2_grpc.py
d3m_automl_rpc/pipeline_pb2.py
d3m_automl_rpc/pipeline_pb2_grpc.py
d3m_automl_rpc/primitive_pb2.py
d3m_automl_rpc/primitive_pb2_grpc.py
d3m_automl_rpc/problem_pb2.py
d3m_automl_rpc/problem_pb2_grpc.py
d3m_automl_rpc/utils.py
d3m_automl_rpc/value_pb2.py
d3m_automl_rpc/value_pb2_grpc.py
d3m_automl_rpc-1.2.4.dist-info/METADATA
d3m_automl_rpc-1.2.4.dist-info/WHEEL
d3m_automl_rpc-1.2.4.dist-info/top_level.txt
d3m_automl_rpc-1.2.4.dist-info/RECORD
