Metadata-Version: 2.1
Name: d3m-automl-rpc
Version: 1.2.4
Summary: gRPC protocol for the AutoML communication.
Home-page: https://gitlab.com/datadrivendiscovery/automl-rpc
Author: DARPA D3M Program
License: Apache-2.0
Platform: UNKNOWN
Classifier: Development Status :: 5 - Production/Stable
Classifier: Intended Audience :: Science/Research
Classifier: Intended Audience :: Developers
Classifier: License :: OSI Approved :: Apache Software License
Classifier: Programming Language :: Python
Classifier: Programming Language :: Python :: 3
Classifier: Topic :: Scientific/Engineering
Classifier: Topic :: Software Development
Requires-Dist: d3m
Requires-Dist: grpcio
Requires-Dist: protobuf (<3.21)
